[
    {
        "pattern": {
            "plateformId": "Landsat",
            "serialId": "5",
            "shortName": "TM",
            "operationalMode": "IM",
            "productType": "TM__GTC_1P"
        },
        "url": "http://brow02.ngeo.eox.at/c/wmts/1.0.0/WMTSCapabilities.xml?SERVICE=WMTS&VERSION=1.0.0&LAYER=Landsat"
    },
    {
        "pattern": {
            "plateformId": "Landsat",
            "serialId": "7",
            "shortName": "*",
            "operationalMode": "*",
            "productType": "*"
        },
        "url": "http://brow02.ngeo.eox.at/c/wmts/1.0.0/WMTSCapabilities.xml?SERVICE=WMTS&VERSION=1.0.0&LAYER=Landsat"
    },
    {
        "pattern": {
            "plateformId": "Landsat"
        },
        "url": "http://brow02.ngeo.eox.at/c/wmts/1.0.0/WMTSCapabilities.xml?SERVICE=WMTS&VERSION=1.0.0&LAYER=Landsat"
    },
    {
        "pattern": {
            "plateformId": "WorldView",
            "serialId": "2",
            "shortName": "*",
            "operationalMode": "*",
            "productType": "*"
        },
        "url": "http://brow02.ngeo.eox.at/c/wmts/1.0.0/WMTSCapabilities.xml?SERVICE=WMTS&VERSION=1.0.0&LAYER=WorldView-2"
    },
    {
        "pattern": {
            "plateformId": "Envisat"
        },
        "url": "http://brow01.ngeo.eox.at/c/wmts/1.0.0/WMTSCapabilities.xml?SERVICE=WMTS&VERSION=1.0.0&LAYER=ENVISAT_ASAR_IMP_1P"
    },
    {
        "pattern": {
            "plateformId": "IKONOS",
            "serialId": "2"
        },
        "url": "http://ngeo-light.evo-pdgs.com/d/wmts/1.0.0/WMTSCapabilities.xml?SERVICE=WMTS&VERSION=1.0.0&LAYER=IKONOS-2"
    },
    {
        "pattern": {
            "plateformId": "Pleiades"
        },
        "url": "http://ngeo-light.evo-pdgs.com/d/wmts/1.0.0/WMTSCapabilities.xml?SERVICE=WMTS&VERSION=1.0.0&LAYER=Pleiades"
    },
    {
        "pattern": {
            "plateformId": "RapidEye"
        },
        "url": "http://ngeo-light.evo-pdgs.com/d/wmts/1.0.0/WMTSCapabilities.xml?SERVICE=WMTS&VERSION=1.0.0&LAYER=RapidEye"
    }
]